symmetric/__init__.py
symmetric/cli/__init__.py
symmetric/cli/core.py
symmetric/cli/utils.py
symmetric/constants.py
symmetric/core.py
symmetric/endpoints.py
symmetric/errors.py
symmetric/helpers.py
symmetric/logging.py
symmetric/openapi/__init__.py
symmetric/openapi/constants.py
symmetric/openapi/docs.py
symmetric/openapi/helpers.py
symmetric/openapi/utils.py
symmetric-3.4.3.dist-info/entry_points.txt
symmetric-3.4.3.dist-info/LICENSE
symmetric-3.4.3.dist-info/WHEEL
symmetric-3.4.3.dist-info/METADATA
symmetric-3.4.3.dist-info/RECORD
