Metadata-Version: 2.1
Name: symmetric
Version: 3.4.3
Summary: A powerful tool to enable super fast module-to-API transformations. Learn in minutes, implement in seconds. Batteries included.
Home-page: https://symmetric.one/
License: MIT
Author: Daniel Leal
Author-email: dlleal@uc.cl
Maintainer: Daniel Leal
Maintainer-email: dlleal@uc.cl
Requires-Python: >=3.6,<4.0
Classifier: Environment :: Web Environment
Classifier: Intended Audience :: Developers
Classifier: License :: OSI Approved :: MIT License
Classifier: Operating System :: OS Independent
Classifier: Programming Language :: Python
Classifier: Programming Language :: Python :: 3
Classifier: Programming Language :: Python :: 3.6
Classifier: Programming Language :: Python :: 3.7
Classifier: Programming Language :: Python :: 3.8
Classifier: Programming Language :: Python :: 3.9
Classifier: Topic :: Internet :: WWW/HTTP :: Dynamic Content
Classifier: Topic :: Internet :: WWW/HTTP :: WSGI :: Application
Classifier: Topic :: Software Development :: Libraries :: Application Frameworks
Classifier: Topic :: Software Development :: Libraries :: Python Modules
Requires-Dist: flask (>=1.1.1,<2.0.0)
Project-URL: Documentation, https://symmetric.one/docs/
Project-URL: Issue Tracker, https://github.com/daleal/symmetric/issues
Project-URL: Repository, https://github.com/daleal/symmetric
